README.rst
aioawait.py
setup.py
aioawait.egg-info/PKG-INFO
aioawait.egg-info/SOURCES.txt
aioawait.egg-info/dependency_links.txt
aioawait.egg-info/top_level.txt
aioawait.egg-info/zip-safe