Metadata-Version: 1.1
Name: aioawait
Version: 8
Summary: Call asynchronous functions of Python 3.4.3 asyncio infrastructure from synchronous code
Home-page: https://bitbucket.org/carlopires/aioawait
Author: Carlo Pires
Author-email: carlopires@gmail.com
License: UNKNOWN
Platform: any
Classifier: Development Status :: 5 - Production/Stable
Classifier: Intended Audience :: Developers
Classifier: License :: OSI Approved :: MIT License
Classifier: Operating System :: OS Independent
Classifier: Programming Language :: Python
Classifier: Programming Language :: Python :: 3
Classifier: Programming Language :: Python :: Implementation :: CPython
Classifier: Topic :: Software Development :: Testing
Classifier: Topic :: Software Development :: Libraries
Classifier: Topic :: Software Development :: Libraries :: Python Modules
Classifier: Topic :: Utilities
